crisprbrain/__init__.py
crisprbrain/client.py
crisprbrain-0.6.1.dist-info/LICENSE
crisprbrain-0.6.1.dist-info/METADATA
crisprbrain-0.6.1.dist-info/WHEEL
crisprbrain-0.6.1.dist-info/top_level.txt
crisprbrain-0.6.1.dist-info/RECORD
