Metadata-Version: 2.1
Name: crisprbrain
Version: 0.6.1
Summary: Data Commons for functional genomics screens in differentiated human cell types
Home-page: https://crisprbrain.org
Author: CRISPRbrain
Author-email: faraz@datatecnica.com
Maintainer: Faraz Faghri
Maintainer-email: faraz.faghri@gmail.com
License: Apache-2.0
Platform: UNKNOWN
Classifier: Programming Language :: Python :: 3 :: Only
Classifier: Development Status :: 4 - Beta
Classifier: License :: OSI Approved :: Apache Software License
Classifier: Operating System :: MacOS :: MacOS X
Classifier: Operating System :: POSIX
Classifier: Topic :: Scientific/Engineering :: Bio-Informatics
Requires-Dist: requests
Requires-Dist: requests-cache
Requires-Dist: pandas
